geochemistrypi/__init__.py
geochemistrypi/_version.py
geochemistrypi/cli.py
geochemistrypi/database.py
geochemistrypi/start_cli_pipeline.py
geochemistrypi/start_dash_pipeline.py
geochemistrypi/auth/__init__.py
geochemistrypi/auth/constants.py
geochemistrypi/auth/dependencies.py
geochemistrypi/auth/router.py
geochemistrypi/auth/schemas.py
geochemistrypi/auth/service.py
geochemistrypi/auth/sql_models.py
geochemistrypi/auth/utils.py
geochemistrypi/data_mining/__init__.py
geochemistrypi/data_mining/cli_pipeline.py
geochemistrypi/data_mining/constants.py
geochemistrypi/data_mining/dash_pipeline.py
geochemistrypi/data_mining/enum.py
geochemistrypi/data_mining/router.py
geochemistrypi/data_mining/schemas.py
geochemistrypi/data_mining/service.py
geochemistrypi/data_mining/sql_models.py
geochemistrypi/data_mining/data/__init__.py
geochemistrypi/data_mining/data/data_readiness.py
geochemistrypi/data_mining/data/feature_engineering.py
geochemistrypi/data_mining/data/imputation.py
geochemistrypi/data_mining/data/inference.py
geochemistrypi/data_mining/data/preprocessing.py
geochemistrypi/data_mining/data/statistic.py
geochemistrypi/data_mining/data/dataset/ApplicationData_Classification.xlsx
geochemistrypi/data_mining/data/dataset/ApplicationData_Regression.xlsx
geochemistrypi/data_mining/data/dataset/Data_AnomalyDetection.xlsx
geochemistrypi/data_mining/data/dataset/Data_Classification.xlsx
geochemistrypi/data_mining/data/dataset/Data_Clustering.xlsx
geochemistrypi/data_mining/data/dataset/Data_Decomposition.xlsx
geochemistrypi/data_mining/data/dataset/Data_Regression.xlsx
geochemistrypi/data_mining/model/__init__.py
geochemistrypi/data_mining/model/_base.py
geochemistrypi/data_mining/model/classification.py
geochemistrypi/data_mining/model/clustering.py
geochemistrypi/data_mining/model/decomposition.py
geochemistrypi/data_mining/model/detection.py
geochemistrypi/data_mining/model/regression.py
geochemistrypi/data_mining/model/func/__init__.py
geochemistrypi-0.7.0.dist-info/METADATA
geochemistrypi-0.7.0.dist-info/WHEEL
geochemistrypi-0.7.0.dist-info/entry_points.txt
geochemistrypi-0.7.0.dist-info/licenses/LICENSE
geochemistrypi-0.7.0.dist-info/RECORD
