Metadata-Version: 2.4
Name: geochemistrypi
Version: 0.7.0
Summary: A highly automated machine learning Python framework dedicating to build up MLOps level 1 software product for data-driven geochemistry discovery
Project-URL: Homepage, https://geochemistrypi.deep-time.org
Project-URL: GitHub, https://github.com/ZJUEarthData/geochemistrypi
Project-URL: Bug Tracker, https://github.com/ZJUEarthData/geochemistrypi/issues
Project-URL: Online Documentation, https://geochemistrypi.readthedocs.io/en/latest/
Author-email: Can He <sanyhew1097618435@163.com>, Jianhao Sun <sjh20171502@gmail.com>, Jianming Zhao <zhaojianming@zju.edu.cn>, Yang Lyu <lyuyang1007@zju.edu.cn>
Maintainer-email: Can He <sanyhew1097618435@163.com>, Jianhao Sun <sjh20171502@gmail.com>, Jianming Zhao <zhaojianming@zju.edu.cn>, Yongkang Shan <kk1361207571@163.com>
License: MIT License
License-File: LICENSE
Keywords: Automated,Continuous Training,Data Mining,Geochemistry Discovery,Geochemistry π,MLOps,Machine Learning,Machine Learning Lifecycle Management,Model Inference
Classifier: License :: OSI Approved :: MIT License
Classifier: Operating System :: OS Independent
Classifier: Programming Language :: Python :: 3.9
Requires-Python: ~=3.9
Requires-Dist: bcrypt==4.0.1
Requires-Dist: dash==2.10.0
Requires-Dist: fastapi==0.95.2
Requires-Dist: flaml==1.0.14
Requires-Dist: imblearn==0.0
Requires-Dist: joblib==1.2.0
Requires-Dist: matplotlib==3.5.2
Requires-Dist: mlflow==2.4.1
Requires-Dist: multipledispatch==0.6.0
Requires-Dist: numpy==1.23.5
Requires-Dist: openpyxl==3.0.10
Requires-Dist: optuna==3.1.1
Requires-Dist: pandas==1.5.2
Requires-Dist: passlib==1.7.4
Requires-Dist: pydantic<2.0.0
Requires-Dist: python-dotenv==1.0.0
Requires-Dist: python-jose[cryptography]
Requires-Dist: python-multipart==0.0.6
Requires-Dist: ray==2.2.0
Requires-Dist: ray[tune]
Requires-Dist: rich==13.3.5
Requires-Dist: scikit-learn==1.1.3
Requires-Dist: scipy==1.10.1
Requires-Dist: seaborn==0.11.0
Requires-Dist: sqlalchemy==2.0.13
Requires-Dist: statsmodels==0.13.2
Requires-Dist: threadpoolctl==3.1.0
Requires-Dist: typer==0.7.0
Requires-Dist: uvicorn==0.22.0
Requires-Dist: xgboost==1.6.2
Provides-Extra: test
Requires-Dist: pytest; extra == 'test'
